{
  "39c5c279": {
    "results": [
      {
        "id": "photo-1542118294-90e12047c078",
        "url": "https://user-images.strikinglycdn.com/res/hrscywv4p/image/upload/f_auto,q_auto,w_4096/unsplashcom/photo-1542118294-90e12047c078",
        "alt": "ARTITECT MACHINERY delivers precision sheet metal folding machines\n            engineered for reliability, speed, and unmatched accuracy. From double\n            folders to versatile metal folding systems. Double Folding Machines Built to Last",
        "aspectRatio": 1.5
      },
      {
        "id": "photo-1665724016980-1abfaac0e24c",
        "url": "https://user-images.strikinglycdn.com/res/hrscywv4p/image/upload/f_auto,q_auto,w_4096/unsplashcom/photo-1665724016980-1abfaac0e24c",
        "alt": "ARTITECT MACHINERY delivers precision sheet metal folding machines\n            engineered for reliability, speed, and unmatched accuracy. From double\n            folders to versatile metal folding systems. Double Folding Machines Built to Last",
        "aspectRatio": 0.67
      },
      {
        "id": "photo-1552997483-a80add0d33f6",
        "url": "https://user-images.strikinglycdn.com/res/hrscywv4p/image/upload/f_auto,q_auto,w_4096/unsplashcom/photo-1552997483-a80add0d33f6",
        "alt": "ARTITECT MACHINERY delivers precision sheet metal folding machines\n            engineered for reliability, speed, and unmatched accuracy. From double\n            folders to versatile metal folding systems. Double Folding Machines Built to Last",
        "aspectRatio": 1.5
      },
      {
        "id": "photo-1665722652044-d9553af6b6a7",
        "url": "https://user-images.strikinglycdn.com/res/hrscywv4p/image/upload/f_auto,q_auto,w_4096/unsplashcom/photo-1665722652044-d9553af6b6a7",
        "alt": "ARTITECT MACHINERY delivers precision sheet metal folding machines\n            engineered for reliability, speed, and unmatched accuracy. From double\n            folders to versatile metal folding systems. Double Folding Machines Built to Last",
        "aspectRatio": 1.5
      },
      {
        "id": "photo-1566280695990-b19918fada4f",
        "url": "https://user-images.strikinglycdn.com/res/hrscywv4p/image/upload/f_auto,q_auto,w_4096/unsplashcom/photo-1566280695990-b19918fada4f",
        "alt": "ARTITECT MACHINERY delivers precision sheet metal folding machines\n            engineered for reliability, speed, and unmatched accuracy. From double\n            folders to versatile metal folding systems. Double Folding Machines Built to Last",
        "aspectRatio": 1.33
      },
      {
        "id": "photo-1665722651505-af56114ca6d1",
        "url": "https://user-images.strikinglycdn.com/res/hrscywv4p/image/upload/f_auto,q_auto,w_4096/unsplashcom/photo-1665722651505-af56114ca6d1",
        "alt": "ARTITECT MACHINERY delivers precision sheet metal folding machines\n            engineered for reliability, speed, and unmatched accuracy. From double\n            folders to versatile metal folding systems. Double Folding Machines Built to Last",
        "aspectRatio": 1.5
      },
      {
        "id": "photo-1494488608440-3a6533519ee2",
        "url": "https://user-images.strikinglycdn.com/res/hrscywv4p/image/upload/f_auto,q_auto,w_4096/unsplashcom/photo-1494488608440-3a6533519ee2",
        "alt": "ARTITECT MACHINERY delivers precision sheet metal folding machines\n            engineered for reliability, speed, and unmatched accuracy. From double\n            folders to versatile metal folding systems. Double Folding Machines Built to Last",
        "aspectRatio": 1.33
      },
      {
        "id": "photo-1675264481024-74e1dcde5d3e",
        "url": "https://user-images.strikinglycdn.com/res/hrscywv4p/image/upload/f_auto,q_auto,w_4096/unsplashcom/photo-1675264481024-74e1dcde5d3e",
        "alt": "ARTITECT MACHINERY delivers precision sheet metal folding machines\n            engineered for reliability, speed, and unmatched accuracy. From double\n            folders to versatile metal folding systems. Double Folding Machines Built to Last",
        "aspectRatio": 1.4
      },
      {
        "id": "photo-1675957955387-9925839ef44f",
        "url": "https://user-images.strikinglycdn.com/res/hrscywv4p/image/upload/f_auto,q_auto,w_4096/unsplashcom/photo-1675957955387-9925839ef44f",
        "alt": "ARTITECT MACHINERY delivers precision sheet metal folding machines\n            engineered for reliability, speed, and unmatched accuracy. From double\n            folders to versatile metal folding systems. Double Folding Machines Built to Last",
        "aspectRatio": 0.75
      },
      {
        "id": "photo-1671452144558-7f0fd0591579",
        "url": "https://user-images.strikinglycdn.com/res/hrscywv4p/image/upload/f_auto,q_auto,w_4096/unsplashcom/photo-1671452144558-7f0fd0591579",
        "alt": "ARTITECT MACHINERY delivers precision sheet metal folding machines\n            engineered for reliability, speed, and unmatched accuracy. From double\n            folders to versatile metal folding systems. Double Folding Machines Built to Last",
        "aspectRatio": 1.33
      },
      {
        "id": "photo-1492010939820-15c3fb3236e4",
        "url": "https://user-images.strikinglycdn.com/res/hrscywv4p/image/upload/f_auto,q_auto,w_4096/unsplashcom/photo-1492010939820-15c3fb3236e4",
        "alt": "ARTITECT MACHINERY delivers precision sheet metal folding machines\n            engineered for reliability, speed, and unmatched accuracy. From double\n            folders to versatile metal folding systems. Double Folding Machines Built to Last",
        "aspectRatio": 1.33
      },
      {
        "id": "photo-1665722651494-563be869f69f",
        "url": "https://user-images.strikinglycdn.com/res/hrscywv4p/image/upload/f_auto,q_auto,w_4096/unsplashcom/photo-1665722651494-563be869f69f",
        "alt": "ARTITECT MACHINERY delivers precision sheet metal folding machines\n            engineered for reliability, speed, and unmatched accuracy. From double\n            folders to versatile metal folding systems. Double Folding Machines Built to Last",
        "aspectRatio": 1.5
      },
      {
        "id": "photo-1618937500626-e183fb8a0607",
        "url": "https://user-images.strikinglycdn.com/res/hrscywv4p/image/upload/f_auto,q_auto,w_4096/unsplashcom/photo-1618937500626-e183fb8a0607",
        "alt": "ARTITECT MACHINERY delivers precision sheet metal folding machines\n            engineered for reliability, speed, and unmatched accuracy. From double\n            folders to versatile metal folding systems. Double Folding Machines Built to Last",
        "aspectRatio": 1.78
      },
      {
        "id": "photo-1575032314279-83caeaf5018c",
        "url": "https://user-images.strikinglycdn.com/res/hrscywv4p/image/upload/f_auto,q_auto,w_4096/unsplashcom/photo-1575032314279-83caeaf5018c",
        "alt": "ARTITECT MACHINERY delivers precision sheet metal folding machines\n            engineered for reliability, speed, and unmatched accuracy. From double\n            folders to versatile metal folding systems. Double Folding Machines Built to Last",
        "aspectRatio": 1.5
      },
      {
        "id": "photo-1656256849937-8803c78ee40b",
        "url": "https://user-images.strikinglycdn.com/res/hrscywv4p/image/upload/f_auto,q_auto,w_4096/unsplashcom/photo-1656256849937-8803c78ee40b",
        "alt": "ARTITECT MACHINERY delivers precision sheet metal folding machines\n            engineered for reliability, speed, and unmatched accuracy. From double\n            folders to versatile metal folding systems. Double Folding Machines Built to Last",
        "aspectRatio": 1.5
      },
      {
        "id": "photo-1575032314023-291d8e41d985",
        "url": "https://user-images.strikinglycdn.com/res/hrscywv4p/image/upload/f_auto,q_auto,w_4096/unsplashcom/photo-1575032314023-291d8e41d985",
        "alt": "ARTITECT MACHINERY delivers precision sheet metal folding machines\n            engineered for reliability, speed, and unmatched accuracy. From double\n            folders to versatile metal folding systems. Double Folding Machines Built to Last",
        "aspectRatio": 1.5
      },
      {
        "id": "photo-1662640455106-f4dba5312c96",
        "url": "https://user-images.strikinglycdn.com/res/hrscywv4p/image/upload/f_auto,q_auto,w_4096/unsplashcom/photo-1662640455106-f4dba5312c96",
        "alt": "ARTITECT MACHINERY delivers precision sheet metal folding machines\n            engineered for reliability, speed, and unmatched accuracy. From double\n            folders to versatile metal folding systems. Double Folding Machines Built to Last",
        "aspectRatio": 1.33
      },
      {
        "id": "photo-1534883496654-aed53cb1c9e0",
        "url": "https://user-images.strikinglycdn.com/res/hrscywv4p/image/upload/f_auto,q_auto,w_4096/unsplashcom/photo-1534883496654-aed53cb1c9e0",
        "alt": "ARTITECT MACHINERY delivers precision sheet metal folding machines\n            engineered for reliability, speed, and unmatched accuracy. From double\n            folders to versatile metal folding systems. Double Folding Machines Built to Last",
        "aspectRatio": 1.5
      },
      {
        "id": "photo-1662001234358-45b7493d2bc0",
        "url": "https://user-images.strikinglycdn.com/res/hrscywv4p/image/upload/f_auto,q_auto,w_4096/unsplashcom/photo-1662001234358-45b7493d2bc0",
        "alt": "ARTITECT MACHINERY delivers precision sheet metal folding machines\n            engineered for reliability, speed, and unmatched accuracy. From double\n            folders to versatile metal folding systems. Double Folding Machines Built to Last",
        "aspectRatio": 1.5
      },
      {
        "id": "photo-1598353893877-36be5be5bf0d",
        "url": "https://user-images.strikinglycdn.com/res/hrscywv4p/image/upload/f_auto,q_auto,w_4096/unsplashcom/photo-1598353893877-36be5be5bf0d",
        "alt": "ARTITECT MACHINERY delivers precision sheet metal folding machines\n            engineered for reliability, speed, and unmatched accuracy. From double\n            folders to versatile metal folding systems. Double Folding Machines Built to Last",
        "aspectRatio": 1.5
      }
    ],
    "_ts": 1781008208511
  },
  "f3fbc61d": {
    "results": [
      {
        "id": "photo-1542118294-90e12047c078",
        "url": "https://user-images.strikinglycdn.com/res/hrscywv4p/image/upload/f_auto,q_auto,w_4096/unsplashcom/photo-1542118294-90e12047c078",
        "alt": "Our flagship double folding machine delivers precise, repeatable bends on both sides of sheet metal in a single pass. Ideal for high-volume production environments. Double Folder Pro",
        "aspectRatio": 1.5
      },
      {
        "id": "photo-1492010939820-15c3fb3236e4",
        "url": "https://user-images.strikinglycdn.com/res/hrscywv4p/image/upload/f_auto,q_auto,w_4096/unsplashcom/photo-1492010939820-15c3fb3236e4",
        "alt": "Our flagship double folding machine delivers precise, repeatable bends on both sides of sheet metal in a single pass. Ideal for high-volume production environments. Double Folder Pro",
        "aspectRatio": 1.33
      },
      {
        "id": "photo-1552997483-a80add0d33f6",
        "url": "https://user-images.strikinglycdn.com/res/hrscywv4p/image/upload/f_auto,q_auto,w_4096/unsplashcom/photo-1552997483-a80add0d33f6",
        "alt": "Our flagship double folding machine delivers precise, repeatable bends on both sides of sheet metal in a single pass. Ideal for high-volume production environments. Double Folder Pro",
        "aspectRatio": 1.5
      },
      {
        "id": "photo-1494488608440-3a6533519ee2",
        "url": "https://user-images.strikinglycdn.com/res/hrscywv4p/image/upload/f_auto,q_auto,w_4096/unsplashcom/photo-1494488608440-3a6533519ee2",
        "alt": "Our flagship double folding machine delivers precise, repeatable bends on both sides of sheet metal in a single pass. Ideal for high-volume production environments. Double Folder Pro",
        "aspectRatio": 1.33
      },
      {
        "id": "photo-1569616689900-c68fc041a5f7",
        "url": "https://user-images.strikinglycdn.com/res/hrscywv4p/image/upload/f_auto,q_auto,w_4096/unsplashcom/photo-1569616689900-c68fc041a5f7",
        "alt": "Our flagship double folding machine delivers precise, repeatable bends on both sides of sheet metal in a single pass. Ideal for high-volume production environments. Double Folder Pro",
        "aspectRatio": 1.5
      },
      {
        "id": "photo-1665722652044-d9553af6b6a7",
        "url": "https://user-images.strikinglycdn.com/res/hrscywv4p/image/upload/f_auto,q_auto,w_4096/unsplashcom/photo-1665722652044-d9553af6b6a7",
        "alt": "Our flagship double folding machine delivers precise, repeatable bends on both sides of sheet metal in a single pass. Ideal for high-volume production environments. Double Folder Pro",
        "aspectRatio": 1.5
      },
      {
        "id": "photo-1665722651505-af56114ca6d1",
        "url": "https://user-images.strikinglycdn.com/res/hrscywv4p/image/upload/f_auto,q_auto,w_4096/unsplashcom/photo-1665722651505-af56114ca6d1",
        "alt": "Our flagship double folding machine delivers precise, repeatable bends on both sides of sheet metal in a single pass. Ideal for high-volume production environments. Double Folder Pro",
        "aspectRatio": 1.5
      },
      {
        "id": "photo-1662001234358-45b7493d2bc0",
        "url": "https://user-images.strikinglycdn.com/res/hrscywv4p/image/upload/f_auto,q_auto,w_4096/unsplashcom/photo-1662001234358-45b7493d2bc0",
        "alt": "Our flagship double folding machine delivers precise, repeatable bends on both sides of sheet metal in a single pass. Ideal for high-volume production environments. Double Folder Pro",
        "aspectRatio": 1.5
      },
      {
        "id": "photo-1566280695990-b19918fada4f",
        "url": "https://user-images.strikinglycdn.com/res/hrscywv4p/image/upload/f_auto,q_auto,w_4096/unsplashcom/photo-1566280695990-b19918fada4f",
        "alt": "Our flagship double folding machine delivers precise, repeatable bends on both sides of sheet metal in a single pass. Ideal for high-volume production environments. Double Folder Pro",
        "aspectRatio": 1.33
      },
      {
        "id": "photo-1665722651494-563be869f69f",
        "url": "https://user-images.strikinglycdn.com/res/hrscywv4p/image/upload/f_auto,q_auto,w_4096/unsplashcom/photo-1665722651494-563be869f69f",
        "alt": "Our flagship double folding machine delivers precise, repeatable bends on both sides of sheet metal in a single pass. Ideal for high-volume production environments. Double Folder Pro",
        "aspectRatio": 1.5
      },
      {
        "id": "photo-1575032314023-291d8e41d985",
        "url": "https://user-images.strikinglycdn.com/res/hrscywv4p/image/upload/f_auto,q_auto,w_4096/unsplashcom/photo-1575032314023-291d8e41d985",
        "alt": "Our flagship double folding machine delivers precise, repeatable bends on both sides of sheet metal in a single pass. Ideal for high-volume production environments. Double Folder Pro",
        "aspectRatio": 1.5
      },
      {
        "id": "photo-1603469727478-6389305b9c0e",
        "url": "https://user-images.strikinglycdn.com/res/hrscywv4p/image/upload/f_auto,q_auto,w_4096/unsplashcom/photo-1603469727478-6389305b9c0e",
        "alt": "Our flagship double folding machine delivers precise, repeatable bends on both sides of sheet metal in a single pass. Ideal for high-volume production environments. Double Folder Pro",
        "aspectRatio": 0.75
      },
      {
        "id": "photo-1665724016980-1abfaac0e24c",
        "url": "https://user-images.strikinglycdn.com/res/hrscywv4p/image/upload/f_auto,q_auto,w_4096/unsplashcom/photo-1665724016980-1abfaac0e24c",
        "alt": "Our flagship double folding machine delivers precise, repeatable bends on both sides of sheet metal in a single pass. Ideal for high-volume production environments. Double Folder Pro",
        "aspectRatio": 0.67
      },
      {
        "id": "photo-1622413107776-b21e55010d6f",
        "url": "https://user-images.strikinglycdn.com/res/hrscywv4p/image/upload/f_auto,q_auto,w_4096/unsplashcom/photo-1622413107776-b21e55010d6f",
        "alt": "Our flagship double folding machine delivers precise, repeatable bends on both sides of sheet metal in a single pass. Ideal for high-volume production environments. Double Folder Pro",
        "aspectRatio": 1.5
      },
      {
        "id": "photo-1584437040362-2463a545965f",
        "url": "https://user-images.strikinglycdn.com/res/hrscywv4p/image/upload/f_auto,q_auto,w_4096/unsplashcom/photo-1584437040362-2463a545965f",
        "alt": "Our flagship double folding machine delivers precise, repeatable bends on both sides of sheet metal in a single pass. Ideal for high-volume production environments. Double Folder Pro",
        "aspectRatio": 0.67
      },
      {
        "id": "photo-1612192867287-426899982f3a",
        "url": "https://user-images.strikinglycdn.com/res/hrscywv4p/image/upload/f_auto,q_auto,w_4096/unsplashcom/photo-1612192867287-426899982f3a",
        "alt": "Our flagship double folding machine delivers precise, repeatable bends on both sides of sheet metal in a single pass. Ideal for high-volume production environments. Double Folder Pro",
        "aspectRatio": 1.5
      },
      {
        "id": "photo-1617664759233-484e38145c07",
        "url": "https://user-images.strikinglycdn.com/res/hrscywv4p/image/upload/f_auto,q_auto,w_4096/unsplashcom/photo-1617664759233-484e38145c07",
        "alt": "Our flagship double folding machine delivers precise, repeatable bends on both sides of sheet metal in a single pass. Ideal for high-volume production environments. Double Folder Pro",
        "aspectRatio": 1.33
      },
      {
        "id": "photo-1671452144558-7f0fd0591579",
        "url": "https://user-images.strikinglycdn.com/res/hrscywv4p/image/upload/f_auto,q_auto,w_4096/unsplashcom/photo-1671452144558-7f0fd0591579",
        "alt": "Our flagship double folding machine delivers precise, repeatable bends on both sides of sheet metal in a single pass. Ideal for high-volume production environments. Double Folder Pro",
        "aspectRatio": 1.33
      },
      {
        "id": "photo-1646497991100-431f910061de",
        "url": "https://user-images.strikinglycdn.com/res/hrscywv4p/image/upload/f_auto,q_auto,w_4096/unsplashcom/photo-1646497991100-431f910061de",
        "alt": "Our flagship double folding machine delivers precise, repeatable bends on both sides of sheet metal in a single pass. Ideal for high-volume production environments. Double Folder Pro",
        "aspectRatio": 1.33
      },
      {
        "id": "photo-1675264481024-74e1dcde5d3e",
        "url": "https://user-images.strikinglycdn.com/res/hrscywv4p/image/upload/f_auto,q_auto,w_4096/unsplashcom/photo-1675264481024-74e1dcde5d3e",
        "alt": "Our flagship double folding machine delivers precise, repeatable bends on both sides of sheet metal in a single pass. Ideal for high-volume production environments. Double Folder Pro",
        "aspectRatio": 1.4
      }
    ],
    "_ts": 1781008208241
  },
  "666729d5": {
    "results": [
      {
        "id": "photo-1552997483-a80add0d33f6",
        "url": "https://user-images.strikinglycdn.com/res/hrscywv4p/image/upload/f_auto,q_auto,w_4096/unsplashcom/photo-1552997483-a80add0d33f6",
        "alt": "The Elite series represents the pinnacle of our metal folding machine lineup. Featuring advanced automation, real-time monitoring, and the highest throughput in its class. Metal Folding Machine Elite",
        "aspectRatio": 1.5
      },
      {
        "id": "photo-1665722651505-af56114ca6d1",
        "url": "https://user-images.strikinglycdn.com/res/hrscywv4p/image/upload/f_auto,q_auto,w_4096/unsplashcom/photo-1665722651505-af56114ca6d1",
        "alt": "The Elite series represents the pinnacle of our metal folding machine lineup. Featuring advanced automation, real-time monitoring, and the highest throughput in its class. Metal Folding Machine Elite",
        "aspectRatio": 1.5
      },
      {
        "id": "photo-1665724016980-1abfaac0e24c",
        "url": "https://user-images.strikinglycdn.com/res/hrscywv4p/image/upload/f_auto,q_auto,w_4096/unsplashcom/photo-1665724016980-1abfaac0e24c",
        "alt": "The Elite series represents the pinnacle of our metal folding machine lineup. Featuring advanced automation, real-time monitoring, and the highest throughput in its class. Metal Folding Machine Elite",
        "aspectRatio": 0.67
      },
      {
        "id": "photo-1492010939820-15c3fb3236e4",
        "url": "https://user-images.strikinglycdn.com/res/hrscywv4p/image/upload/f_auto,q_auto,w_4096/unsplashcom/photo-1492010939820-15c3fb3236e4",
        "alt": "The Elite series represents the pinnacle of our metal folding machine lineup. Featuring advanced automation, real-time monitoring, and the highest throughput in its class. Metal Folding Machine Elite",
        "aspectRatio": 1.33
      },
      {
        "id": "photo-1525726980977-5ee8d30cbafc",
        "url": "https://user-images.strikinglycdn.com/res/hrscywv4p/image/upload/f_auto,q_auto,w_4096/unsplashcom/photo-1525726980977-5ee8d30cbafc",
        "alt": "The Elite series represents the pinnacle of our metal folding machine lineup. Featuring advanced automation, real-time monitoring, and the highest throughput in its class. Metal Folding Machine Elite",
        "aspectRatio": 1.5
      },
      {
        "id": "photo-1542118294-90e12047c078",
        "url": "https://user-images.strikinglycdn.com/res/hrscywv4p/image/upload/f_auto,q_auto,w_4096/unsplashcom/photo-1542118294-90e12047c078",
        "alt": "The Elite series represents the pinnacle of our metal folding machine lineup. Featuring advanced automation, real-time monitoring, and the highest throughput in its class. Metal Folding Machine Elite",
        "aspectRatio": 1.5
      },
      {
        "id": "photo-1675957955387-9925839ef44f",
        "url": "https://user-images.strikinglycdn.com/res/hrscywv4p/image/upload/f_auto,q_auto,w_4096/unsplashcom/photo-1675957955387-9925839ef44f",
        "alt": "The Elite series represents the pinnacle of our metal folding machine lineup. Featuring advanced automation, real-time monitoring, and the highest throughput in its class. Metal Folding Machine Elite",
        "aspectRatio": 0.75
      },
      {
        "id": "photo-1494488608440-3a6533519ee2",
        "url": "https://user-images.strikinglycdn.com/res/hrscywv4p/image/upload/f_auto,q_auto,w_4096/unsplashcom/photo-1494488608440-3a6533519ee2",
        "alt": "The Elite series represents the pinnacle of our metal folding machine lineup. Featuring advanced automation, real-time monitoring, and the highest throughput in its class. Metal Folding Machine Elite",
        "aspectRatio": 1.33
      },
      {
        "id": "photo-1633081399469-b39ea0bc857e",
        "url": "https://user-images.strikinglycdn.com/res/hrscywv4p/image/upload/f_auto,q_auto,w_4096/unsplashcom/photo-1633081399469-b39ea0bc857e",
        "alt": "The Elite series represents the pinnacle of our metal folding machine lineup. Featuring advanced automation, real-time monitoring, and the highest throughput in its class. Metal Folding Machine Elite",
        "aspectRatio": 1.5
      },
      {
        "id": "photo-1671452144558-7f0fd0591579",
        "url": "https://user-images.strikinglycdn.com/res/hrscywv4p/image/upload/f_auto,q_auto,w_4096/unsplashcom/photo-1671452144558-7f0fd0591579",
        "alt": "The Elite series represents the pinnacle of our metal folding machine lineup. Featuring advanced automation, real-time monitoring, and the highest throughput in its class. Metal Folding Machine Elite",
        "aspectRatio": 1.33
      },
      {
        "id": "photo-1612192867287-426899982f3a",
        "url": "https://user-images.strikinglycdn.com/res/hrscywv4p/image/upload/f_auto,q_auto,w_4096/unsplashcom/photo-1612192867287-426899982f3a",
        "alt": "The Elite series represents the pinnacle of our metal folding machine lineup. Featuring advanced automation, real-time monitoring, and the highest throughput in its class. Metal Folding Machine Elite",
        "aspectRatio": 1.5
      },
      {
        "id": "photo-1665724016409-0bb89a89812b",
        "url": "https://user-images.strikinglycdn.com/res/hrscywv4p/image/upload/f_auto,q_auto,w_4096/unsplashcom/photo-1665724016409-0bb89a89812b",
        "alt": "The Elite series represents the pinnacle of our metal folding machine lineup. Featuring advanced automation, real-time monitoring, and the highest throughput in its class. Metal Folding Machine Elite",
        "aspectRatio": 1.5
      },
      {
        "id": "photo-1572266904486-19b9bbf3766d",
        "url": "https://user-images.strikinglycdn.com/res/hrscywv4p/image/upload/f_auto,q_auto,w_4096/unsplashcom/photo-1572266904486-19b9bbf3766d",
        "alt": "The Elite series represents the pinnacle of our metal folding machine lineup. Featuring advanced automation, real-time monitoring, and the highest throughput in its class. Metal Folding Machine Elite",
        "aspectRatio": 1.5
      },
      {
        "id": "photo-1556978943-6d93d7a19bf5",
        "url": "https://user-images.strikinglycdn.com/res/hrscywv4p/image/upload/f_auto,q_auto,w_4096/unsplashcom/photo-1556978943-6d93d7a19bf5",
        "alt": "The Elite series represents the pinnacle of our metal folding machine lineup. Featuring advanced automation, real-time monitoring, and the highest throughput in its class. Metal Folding Machine Elite",
        "aspectRatio": 0.75
      },
      {
        "id": "photo-1575032314023-291d8e41d985",
        "url": "https://user-images.strikinglycdn.com/res/hrscywv4p/image/upload/f_auto,q_auto,w_4096/unsplashcom/photo-1575032314023-291d8e41d985",
        "alt": "The Elite series represents the pinnacle of our metal folding machine lineup. Featuring advanced automation, real-time monitoring, and the highest throughput in its class. Metal Folding Machine Elite",
        "aspectRatio": 1.5
      },
      {
        "id": "photo-1595420504314-e5a0b4fd0fe6",
        "url": "https://user-images.strikinglycdn.com/res/hrscywv4p/image/upload/f_auto,q_auto,w_4096/unsplashcom/photo-1595420504314-e5a0b4fd0fe6",
        "alt": "The Elite series represents the pinnacle of our metal folding machine lineup. Featuring advanced automation, real-time monitoring, and the highest throughput in its class. Metal Folding Machine Elite",
        "aspectRatio": 1.51
      },
      {
        "id": "photo-1615767436465-8d8c8190fab3",
        "url": "https://user-images.strikinglycdn.com/res/hrscywv4p/image/upload/f_auto,q_auto,w_4096/unsplashcom/photo-1615767436465-8d8c8190fab3",
        "alt": "The Elite series represents the pinnacle of our metal folding machine lineup. Featuring advanced automation, real-time monitoring, and the highest throughput in its class. Metal Folding Machine Elite",
        "aspectRatio": 1.5
      },
      {
        "id": "photo-1553591866-b6b58649d6ea",
        "url": "https://user-images.strikinglycdn.com/res/hrscywv4p/image/upload/f_auto,q_auto,w_4096/unsplashcom/flagged/photo-1553591866-b6b58649d6ea",
        "alt": "The Elite series represents the pinnacle of our metal folding machine lineup. Featuring advanced automation, real-time monitoring, and the highest throughput in its class. Metal Folding Machine Elite",
        "aspectRatio": 1.36
      },
      {
        "id": "photo-1608644895638-40c73f3e35f3",
        "url": "https://user-images.strikinglycdn.com/res/hrscywv4p/image/upload/f_auto,q_auto,w_4096/unsplashcom/photo-1608644895638-40c73f3e35f3",
        "alt": "The Elite series represents the pinnacle of our metal folding machine lineup. Featuring advanced automation, real-time monitoring, and the highest throughput in its class. Metal Folding Machine Elite",
        "aspectRatio": 0.75
      },
      {
        "id": "photo-1571492627704-a06b63698d91",
        "url": "https://user-images.strikinglycdn.com/res/hrscywv4p/image/upload/f_auto,q_auto,w_4096/unsplashcom/photo-1571492627704-a06b63698d91",
        "alt": "The Elite series represents the pinnacle of our metal folding machine lineup. Featuring advanced automation, real-time monitoring, and the highest throughput in its class. Metal Folding Machine Elite",
        "aspectRatio": 0.67
      }
    ],
    "_ts": 1781008208241
  },
  "eb08b591": {
    "results": [
      {
        "id": "photo-1542118294-90e12047c078",
        "url": "https://user-images.strikinglycdn.com/res/hrscywv4p/image/upload/f_auto,q_auto,w_4096/unsplashcom/photo-1542118294-90e12047c078",
        "alt": "The X1 sheet metal folding machine handles a wide range of materials and thicknesses with ease. Built for workshops that demand flexibility without compromising accuracy. Sheet Metal Folder X1",
        "aspectRatio": 1.5
      },
      {
        "id": "photo-1552997483-a80add0d33f6",
        "url": "https://user-images.strikinglycdn.com/res/hrscywv4p/image/upload/f_auto,q_auto,w_4096/unsplashcom/photo-1552997483-a80add0d33f6",
        "alt": "The X1 sheet metal folding machine handles a wide range of materials and thicknesses with ease. Built for workshops that demand flexibility without compromising accuracy. Sheet Metal Folder X1",
        "aspectRatio": 1.5
      },
      {
        "id": "photo-1492010939820-15c3fb3236e4",
        "url": "https://user-images.strikinglycdn.com/res/hrscywv4p/image/upload/f_auto,q_auto,w_4096/unsplashcom/photo-1492010939820-15c3fb3236e4",
        "alt": "The X1 sheet metal folding machine handles a wide range of materials and thicknesses with ease. Built for workshops that demand flexibility without compromising accuracy. Sheet Metal Folder X1",
        "aspectRatio": 1.33
      },
      {
        "id": "photo-1569616689900-c68fc041a5f7",
        "url": "https://user-images.strikinglycdn.com/res/hrscywv4p/image/upload/f_auto,q_auto,w_4096/unsplashcom/photo-1569616689900-c68fc041a5f7",
        "alt": "The X1 sheet metal folding machine handles a wide range of materials and thicknesses with ease. Built for workshops that demand flexibility without compromising accuracy. Sheet Metal Folder X1",
        "aspectRatio": 1.5
      },
      {
        "id": "photo-1665722652044-d9553af6b6a7",
        "url": "https://user-images.strikinglycdn.com/res/hrscywv4p/image/upload/f_auto,q_auto,w_4096/unsplashcom/photo-1665722652044-d9553af6b6a7",
        "alt": "The X1 sheet metal folding machine handles a wide range of materials and thicknesses with ease. Built for workshops that demand flexibility without compromising accuracy. Sheet Metal Folder X1",
        "aspectRatio": 1.5
      },
      {
        "id": "photo-1662640455106-f4dba5312c96",
        "url": "https://user-images.strikinglycdn.com/res/hrscywv4p/image/upload/f_auto,q_auto,w_4096/unsplashcom/photo-1662640455106-f4dba5312c96",
        "alt": "The X1 sheet metal folding machine handles a wide range of materials and thicknesses with ease. Built for workshops that demand flexibility without compromising accuracy. Sheet Metal Folder X1",
        "aspectRatio": 1.33
      },
      {
        "id": "photo-1671452144558-7f0fd0591579",
        "url": "https://user-images.strikinglycdn.com/res/hrscywv4p/image/upload/f_auto,q_auto,w_4096/unsplashcom/photo-1671452144558-7f0fd0591579",
        "alt": "The X1 sheet metal folding machine handles a wide range of materials and thicknesses with ease. Built for workshops that demand flexibility without compromising accuracy. Sheet Metal Folder X1",
        "aspectRatio": 1.33
      },
      {
        "id": "photo-1656256849937-8803c78ee40b",
        "url": "https://user-images.strikinglycdn.com/res/hrscywv4p/image/upload/f_auto,q_auto,w_4096/unsplashcom/photo-1656256849937-8803c78ee40b",
        "alt": "The X1 sheet metal folding machine handles a wide range of materials and thicknesses with ease. Built for workshops that demand flexibility without compromising accuracy. Sheet Metal Folder X1",
        "aspectRatio": 1.5
      },
      {
        "id": "photo-1665722651505-af56114ca6d1",
        "url": "https://user-images.strikinglycdn.com/res/hrscywv4p/image/upload/f_auto,q_auto,w_4096/unsplashcom/photo-1665722651505-af56114ca6d1",
        "alt": "The X1 sheet metal folding machine handles a wide range of materials and thicknesses with ease. Built for workshops that demand flexibility without compromising accuracy. Sheet Metal Folder X1",
        "aspectRatio": 1.5
      },
      {
        "id": "photo-1612192867287-426899982f3a",
        "url": "https://user-images.strikinglycdn.com/res/hrscywv4p/image/upload/f_auto,q_auto,w_4096/unsplashcom/photo-1612192867287-426899982f3a",
        "alt": "The X1 sheet metal folding machine handles a wide range of materials and thicknesses with ease. Built for workshops that demand flexibility without compromising accuracy. Sheet Metal Folder X1",
        "aspectRatio": 1.5
      },
      {
        "id": "photo-1575032314023-291d8e41d985",
        "url": "https://user-images.strikinglycdn.com/res/hrscywv4p/image/upload/f_auto,q_auto,w_4096/unsplashcom/photo-1575032314023-291d8e41d985",
        "alt": "The X1 sheet metal folding machine handles a wide range of materials and thicknesses with ease. Built for workshops that demand flexibility without compromising accuracy. Sheet Metal Folder X1",
        "aspectRatio": 1.5
      },
      {
        "id": "photo-1612352964909-b12ececa371f",
        "url": "https://user-images.strikinglycdn.com/res/hrscywv4p/image/upload/f_auto,q_auto,w_4096/unsplashcom/photo-1612352964909-b12ececa371f",
        "alt": "The X1 sheet metal folding machine handles a wide range of materials and thicknesses with ease. Built for workshops that demand flexibility without compromising accuracy. Sheet Metal Folder X1",
        "aspectRatio": 1.33
      },
      {
        "id": "photo-1494488608440-3a6533519ee2",
        "url": "https://user-images.strikinglycdn.com/res/hrscywv4p/image/upload/f_auto,q_auto,w_4096/unsplashcom/photo-1494488608440-3a6533519ee2",
        "alt": "The X1 sheet metal folding machine handles a wide range of materials and thicknesses with ease. Built for workshops that demand flexibility without compromising accuracy. Sheet Metal Folder X1",
        "aspectRatio": 1.33
      },
      {
        "id": "photo-1566280695990-b19918fada4f",
        "url": "https://user-images.strikinglycdn.com/res/hrscywv4p/image/upload/f_auto,q_auto,w_4096/unsplashcom/photo-1566280695990-b19918fada4f",
        "alt": "The X1 sheet metal folding machine handles a wide range of materials and thicknesses with ease. Built for workshops that demand flexibility without compromising accuracy. Sheet Metal Folder X1",
        "aspectRatio": 1.33
      },
      {
        "id": "photo-1659993447118-f9a229832042",
        "url": "https://user-images.strikinglycdn.com/res/hrscywv4p/image/upload/f_auto,q_auto,w_4096/unsplashcom/photo-1659993447118-f9a229832042",
        "alt": "The X1 sheet metal folding machine handles a wide range of materials and thicknesses with ease. Built for workshops that demand flexibility without compromising accuracy. Sheet Metal Folder X1",
        "aspectRatio": 1.5
      },
      {
        "id": "photo-1660578150623-2e3790e214a9",
        "url": "https://user-images.strikinglycdn.com/res/hrscywv4p/image/upload/f_auto,q_auto,w_4096/unsplashcom/photo-1660578150623-2e3790e214a9",
        "alt": "The X1 sheet metal folding machine handles a wide range of materials and thicknesses with ease. Built for workshops that demand flexibility without compromising accuracy. Sheet Metal Folder X1",
        "aspectRatio": 1.5
      },
      {
        "id": "photo-1556978943-6d93d7a19bf5",
        "url": "https://user-images.strikinglycdn.com/res/hrscywv4p/image/upload/f_auto,q_auto,w_4096/unsplashcom/photo-1556978943-6d93d7a19bf5",
        "alt": "The X1 sheet metal folding machine handles a wide range of materials and thicknesses with ease. Built for workshops that demand flexibility without compromising accuracy. Sheet Metal Folder X1",
        "aspectRatio": 0.75
      },
      {
        "id": "photo-1665724016980-1abfaac0e24c",
        "url": "https://user-images.strikinglycdn.com/res/hrscywv4p/image/upload/f_auto,q_auto,w_4096/unsplashcom/photo-1665724016980-1abfaac0e24c",
        "alt": "The X1 sheet metal folding machine handles a wide range of materials and thicknesses with ease. Built for workshops that demand flexibility without compromising accuracy. Sheet Metal Folder X1",
        "aspectRatio": 0.67
      },
      {
        "id": "photo-1532945173481-1878c8f12dbb",
        "url": "https://user-images.strikinglycdn.com/res/hrscywv4p/image/upload/f_auto,q_auto,w_4096/unsplashcom/photo-1532945173481-1878c8f12dbb",
        "alt": "The X1 sheet metal folding machine handles a wide range of materials and thicknesses with ease. Built for workshops that demand flexibility without compromising accuracy. Sheet Metal Folder X1",
        "aspectRatio": 1.33
      },
      {
        "id": "photo-1652991402799-af36591b1fdd",
        "url": "https://user-images.strikinglycdn.com/res/hrscywv4p/image/upload/f_auto,q_auto,w_4096/unsplashcom/photo-1652991402799-af36591b1fdd",
        "alt": "The X1 sheet metal folding machine handles a wide range of materials and thicknesses with ease. Built for workshops that demand flexibility without compromising accuracy. Sheet Metal Folder X1",
        "aspectRatio": 1.5
      }
    ],
    "_ts": 1781008208241
  },
  "455d3d67": {
    "results": [
      {
        "id": "photo-1556978943-6d93d7a19bf5",
        "url": "https://user-images.strikinglycdn.com/res/hrscywv4p/image/upload/f_auto,q_auto,w_4096/unsplashcom/photo-1556978943-6d93d7a19bf5",
        "alt": "Engineered for workshops with limited space, the Compact metal folder machine packs full-size performance into a smaller footprint without any trade-offs in precision. Metal Folder Compact",
        "aspectRatio": 0.75
      },
      {
        "id": "photo-1552997483-a80add0d33f6",
        "url": "https://user-images.strikinglycdn.com/res/hrscywv4p/image/upload/f_auto,q_auto,w_4096/unsplashcom/photo-1552997483-a80add0d33f6",
        "alt": "Engineered for workshops with limited space, the Compact metal folder machine packs full-size performance into a smaller footprint without any trade-offs in precision. Metal Folder Compact",
        "aspectRatio": 1.5
      },
      {
        "id": "photo-1542118294-90e12047c078",
        "url": "https://user-images.strikinglycdn.com/res/hrscywv4p/image/upload/f_auto,q_auto,w_4096/unsplashcom/photo-1542118294-90e12047c078",
        "alt": "Engineered for workshops with limited space, the Compact metal folder machine packs full-size performance into a smaller footprint without any trade-offs in precision. Metal Folder Compact",
        "aspectRatio": 1.5
      },
      {
        "id": "photo-1492010939820-15c3fb3236e4",
        "url": "https://user-images.strikinglycdn.com/res/hrscywv4p/image/upload/f_auto,q_auto,w_4096/unsplashcom/photo-1492010939820-15c3fb3236e4",
        "alt": "Engineered for workshops with limited space, the Compact metal folder machine packs full-size performance into a smaller footprint without any trade-offs in precision. Metal Folder Compact",
        "aspectRatio": 1.33
      },
      {
        "id": "photo-1494488608440-3a6533519ee2",
        "url": "https://user-images.strikinglycdn.com/res/hrscywv4p/image/upload/f_auto,q_auto,w_4096/unsplashcom/photo-1494488608440-3a6533519ee2",
        "alt": "Engineered for workshops with limited space, the Compact metal folder machine packs full-size performance into a smaller footprint without any trade-offs in precision. Metal Folder Compact",
        "aspectRatio": 1.33
      },
      {
        "id": "photo-1675957955387-9925839ef44f",
        "url": "https://user-images.strikinglycdn.com/res/hrscywv4p/image/upload/f_auto,q_auto,w_4096/unsplashcom/photo-1675957955387-9925839ef44f",
        "alt": "Engineered for workshops with limited space, the Compact metal folder machine packs full-size performance into a smaller footprint without any trade-offs in precision. Metal Folder Compact",
        "aspectRatio": 0.75
      },
      {
        "id": "photo-1477301404110-b06b147fe49a",
        "url": "https://user-images.strikinglycdn.com/res/hrscywv4p/image/upload/f_auto,q_auto,w_4096/unsplashcom/photo-1477301404110-b06b147fe49a",
        "alt": "Engineered for workshops with limited space, the Compact metal folder machine packs full-size performance into a smaller footprint without any trade-offs in precision. Metal Folder Compact",
        "aspectRatio": 0.75
      },
      {
        "id": "photo-1646497991100-431f910061de",
        "url": "https://user-images.strikinglycdn.com/res/hrscywv4p/image/upload/f_auto,q_auto,w_4096/unsplashcom/photo-1646497991100-431f910061de",
        "alt": "Engineered for workshops with limited space, the Compact metal folder machine packs full-size performance into a smaller footprint without any trade-offs in precision. Metal Folder Compact",
        "aspectRatio": 1.33
      },
      {
        "id": "photo-1598299803213-d894fb2ab97d",
        "url": "https://user-images.strikinglycdn.com/res/hrscywv4p/image/upload/f_auto,q_auto,w_4096/unsplashcom/photo-1598299803213-d894fb2ab97d",
        "alt": "Engineered for workshops with limited space, the Compact metal folder machine packs full-size performance into a smaller footprint without any trade-offs in precision. Metal Folder Compact",
        "aspectRatio": 1.5
      },
      {
        "id": "photo-1568226189297-94b57eff8782",
        "url": "https://user-images.strikinglycdn.com/res/hrscywv4p/image/upload/f_auto,q_auto,w_4096/unsplashcom/photo-1568226189297-94b57eff8782",
        "alt": "Engineered for workshops with limited space, the Compact metal folder machine packs full-size performance into a smaller footprint without any trade-offs in precision. Metal Folder Compact",
        "aspectRatio": 1.78
      },
      {
        "id": "photo-1572266904486-19b9bbf3766d",
        "url": "https://user-images.strikinglycdn.com/res/hrscywv4p/image/upload/f_auto,q_auto,w_4096/unsplashcom/photo-1572266904486-19b9bbf3766d",
        "alt": "Engineered for workshops with limited space, the Compact metal folder machine packs full-size performance into a smaller footprint without any trade-offs in precision. Metal Folder Compact",
        "aspectRatio": 1.5
      },
      {
        "id": "photo-1656341503406-adb90f16a444",
        "url": "https://user-images.strikinglycdn.com/res/hrscywv4p/image/upload/f_auto,q_auto,w_4096/unsplashcom/photo-1656341503406-adb90f16a444",
        "alt": "Engineered for workshops with limited space, the Compact metal folder machine packs full-size performance into a smaller footprint without any trade-offs in precision. Metal Folder Compact",
        "aspectRatio": 1.51
      },
      {
        "id": "photo-1610409013012-21aed6283823",
        "url": "https://user-images.strikinglycdn.com/res/hrscywv4p/image/upload/f_auto,q_auto,w_4096/unsplashcom/photo-1610409013012-21aed6283823",
        "alt": "Engineered for workshops with limited space, the Compact metal folder machine packs full-size performance into a smaller footprint without any trade-offs in precision. Metal Folder Compact",
        "aspectRatio": 0.67
      },
      {
        "id": "photo-1528478160938-d846556f801a",
        "url": "https://user-images.strikinglycdn.com/res/hrscywv4p/image/upload/f_auto,q_auto,w_4096/unsplashcom/photo-1528478160938-d846556f801a",
        "alt": "Engineered for workshops with limited space, the Compact metal folder machine packs full-size performance into a smaller footprint without any trade-offs in precision. Metal Folder Compact",
        "aspectRatio": 1.5
      },
      {
        "id": "photo-1559218603-5c5637481f3a",
        "url": "https://user-images.strikinglycdn.com/res/hrscywv4p/image/upload/f_auto,q_auto,w_4096/unsplashcom/photo-1559218603-5c5637481f3a",
        "alt": "Engineered for workshops with limited space, the Compact metal folder machine packs full-size performance into a smaller footprint without any trade-offs in precision. Metal Folder Compact",
        "aspectRatio": 1.5
      },
      {
        "id": "photo-1575839127403-433ec253fb72",
        "url": "https://user-images.strikinglycdn.com/res/hrscywv4p/image/upload/f_auto,q_auto,w_4096/unsplashcom/photo-1575839127403-433ec253fb72",
        "alt": "Engineered for workshops with limited space, the Compact metal folder machine packs full-size performance into a smaller footprint without any trade-offs in precision. Metal Folder Compact",
        "aspectRatio": 1.5
      },
      {
        "id": "photo-1616802873071-5f09bbef7e86",
        "url": "https://user-images.strikinglycdn.com/res/hrscywv4p/image/upload/f_auto,q_auto,w_4096/unsplashcom/photo-1616802873071-5f09bbef7e86",
        "alt": "Engineered for workshops with limited space, the Compact metal folder machine packs full-size performance into a smaller footprint without any trade-offs in precision. Metal Folder Compact",
        "aspectRatio": 0.75
      },
      {
        "id": "photo-1631561380569-051f41bd480b",
        "url": "https://user-images.strikinglycdn.com/res/hrscywv4p/image/upload/f_auto,q_auto,w_4096/unsplashcom/photo-1631561380569-051f41bd480b",
        "alt": "Engineered for workshops with limited space, the Compact metal folder machine packs full-size performance into a smaller footprint without any trade-offs in precision. Metal Folder Compact",
        "aspectRatio": 1.5
      },
      {
        "id": "photo-1549037174-4caa0ccf11b0",
        "url": "https://user-images.strikinglycdn.com/res/hrscywv4p/image/upload/f_auto,q_auto,w_4096/unsplashcom/photo-1549037174-4caa0ccf11b0",
        "alt": "Engineered for workshops with limited space, the Compact metal folder machine packs full-size performance into a smaller footprint without any trade-offs in precision. Metal Folder Compact",
        "aspectRatio": 1.5
      },
      {
        "id": "photo-1633504095688-4a1e36d6b3a5",
        "url": "https://user-images.strikinglycdn.com/res/hrscywv4p/image/upload/f_auto,q_auto,w_4096/unsplashcom/photo-1633504095688-4a1e36d6b3a5",
        "alt": "Engineered for workshops with limited space, the Compact metal folder machine packs full-size performance into a smaller footprint without any trade-offs in precision. Metal Folder Compact",
        "aspectRatio": 1.5
      }
    ],
    "_ts": 1781008208241
  }
}